{"title":"Bhakti Literature Quiz","exam":"TNPSC","subject":"Tamil","topic":"Bhakti Literature","questions":[{"question":"தேவாரம் பாடியவர்கள் யார்?","options":["ஆழ்வார்கள்","நாயன்மார்கள்","அடியார்கள்","முனிவர்கள்"],"answer_index":1,"explanation":"தேவாரம் சைவ நாயன்மார்களால் பாடப்பட்டது. திருஞானசம்பந்தர், திருநாவுக்கரசர் (அப்பர்), சுந்தரர் ஆகிய மூவர் பாடியவை சேர்க்கப்பட்டு திருமுறையாக வகைப்படுத்தப்பட்டது.","difficulty":"medium"},{"question":"திவ்யப்பிரபந்தம் பாடியவர்கள் யார்?","options":["நாயன்மார்கள்","ஆழ்வார்கள்","நாத முனிகள்","வைணவ அடியார்கள்"],"answer_index":1,"explanation":"திவ்யப்பிரபந்தம் 12 ஆழ்வார்களால் பாடப்பட்டது. 4000 பாசுரங்களை கொண்டது. நம்மாழ்வாரின் திருவாய்மொழி இதில் மிக முக்கியமானது.","difficulty":"medium"},{"question":"தேவாரம் என்பது என்ன?","options":["வைணவ பாடல்கள்","சைவ சமயக் கவிஞர்களான மூவர் (அப்பர், சம்பந்தர், சுந்தரர்) பாடிய சிவன் மீதான பக்திப் பாடல்கள்","கடவுளின் திருவருளை பாடும் பாடல்","தமிழ் கல்வி நூல்"],"answer_index":1,"explanation":"தேவாரம் — சைவ சமய 'மூவர்' எனப்படும் அப்பர் (திருநாவுக்கரசர்), திருஞானசம்பந்தர், சுந்தரர் ஆகியோர் பாடிய சிவன் மீதான தமிழ் பக்திப் பாடல்கள் (சுமார் கி.பி. 7-8ஆம் நூற்றாண்டு). திருமுறைகளில் 1-7 ஆகும்.","difficulty":"medium"},{"question":"நாலாயிரத் திவ்வியப் பிரபந்தம் என்பது என்ன?","options":["சைவப் பாடல்கள்","12 ஆழ்வார்கள் பாடிய வைணவ பக்திப் பாடல்கள் 4000 கொண்ட தொகுப்பு","கி.பி. 12ஆம் நூற்றாண்டு இலக்கியம்","திருவள்ளுவர் பாடல்கள்"],"answer_index":1,"explanation":"நாலாயிரத் திவ்வியப் பிரபந்தம் — 12 ஆழ்வார்கள் பாடிய திருமால் (விஷ்ணு) மீதான 4000 பக்திப் பாடல்கள். கி.பி. 6–9 நூற்றாண்டுகளில் பாடப்பட்டு, நாதமுனி (கி.பி. 10ஆம் நூற்றாண்டு) தொகுத்தார்.","difficulty":"medium"},{"question":"ஆழ்வார்கள் மொத்தம் எத்தனை பேர்?","options":["10","12","63","18"],"answer_index":1,"explanation":"ஆழ்வார்கள் 12 பேர். இவர்கள் திருமால் பக்தர்கள். 63 நாயன்மார்கள் சைவத்தில் சிவ பக்தர்கள். ஆண்டாள் ஒரே பெண் ஆழ்வார். நம்மாழ்வார் திருவாய்மொழி பாடியவர்.","difficulty":"easy"},{"question":"நாயன்மார்கள் மொத்தம் எத்தனை பேர்?","options":["12","18","63","100"],"answer_index":2,"explanation":"நாயன்மார்கள் 63 பேர். இவர்கள் சைவ சமயத்தின் சிவ பக்தர்கள். பெரியபுராணம் என்ற நூல் 63 நாயன்மார்களின் வாழ்க்கை வரலாற்றை கூறுகிறது. சேக்கிழார் இந்த நூலை இயற்றினார்.","difficulty":"easy"},{"question":"மகாகவி பாரதியார் என்று அழைக்கப்படுபவர் யார்?","options":["கம்பர்","சுப்பிரமணிய பாரதி","பாரதிதாசன்","திருவள்ளுவர்"],"answer_index":1,"explanation":"சுப்பிரமணிய பாரதி (1882-1921) — 'மகாகவி பாரதியார்' என்று அழைக்கப்படுகிறார். தேசபக்தி, பெண்ணுரிமை, சமத்துவம் பாடினார். 'அச்சமில்லை அச்சமில்லை', 'வந்தே மாதரம்' புகழ்பெற்ற பாடல்கள்.","difficulty":"easy"},{"question":"இறைவனிடம் அன்பு செய்வதையே முதன்மையான வழிபாடாகக் கொண்ட இயக்கம் எது?","options":["சமணம்","பௌத்தம்","பக்தி இயக்கம்","சாக்தம்"],"answer_index":2,"explanation":"இறைவனிடம் பக்தி (அன்பு) செலுத்துவதையே முதன்மைப்படுத்தியது பக்தி இயக்கம். இது ஆழ்வார்கள் மற்றும் நாயன்மார்களால் வளர்க்கப்பட்டது.","difficulty":"easy"},{"question":"தேவாரம் எழுதிய மூவர் அடங்கிய தொகுப்பு எது?","options":["நாலாயிர திவ்வியப் பிரபந்தம்","தேவாரத் திருமுறை","திருவாசகம்","திருக்குறள்"],"answer_index":1,"explanation":"திருஞானசம்பந்தர், திருநாவுக்கரசர், சுந்தரர் ஆகிய மூவரும் இயற்றிய பாடல்களின் தொகுப்பே தேவாரத் திருமுறை ஆகும்.","difficulty":"easy"},{"question":"நாலாயிர திவ்வியப் பிரபந்தத்தைத் தொகுத்தவர் யார்?","options":["ஆண்டாள்","நாதமுனிகள்","திருமங்கையாழ்வார்","பெரியாழ்வார்"],"answer_index":1,"explanation":"வைணவ ஆழ்வார்கள் பாடிய பாடல்களை நாதமுனிகள் தொகுத்து நாலாயிர திவ்வியப் பிரபந்தம் ஆக்கினார்.","difficulty":"easy"},{"question":"பன்னிரு ஆழ்வார்களில் ஒருவரும், பெண்ணுமானவர் யார்?","options":["திருப்பாணாழ்வார்","ஆண்டாள்","குலசேகராழ்வார்","தொண்டரடிப்பொடியாழ்வார்"],"answer_index":1,"explanation":"ஆண்டாள் பன்னிரு ஆழ்வார்களில் ஒரே பெண் ஆழ்வார் ஆவார். இவர் பெரியாழ்வாரின் மகளாக வளர்ந்தவர்.","difficulty":"easy"},{"question":"திருக்குறளின் பகுதிகள் (அதிகாரங்கள்) எத்தனை உள்ளன?","options":["133","138","122","130"],"answer_index":0,"explanation":"திருக்குறளில் 133 அதிகாரங்கள் (பகுதிகள்) உள்ளன. ஒவ்வொரு அதிகாரமும் 10 குறள்களைக் கொண்டது.","difficulty":"easy"},{"question":"சங்க இலக்கியங்களில் புறத்திணைப் பாடல்கள் அதிகம் கொண்ட நூல் எது?","options":["அகநானூறு","குறுந்தொகை","புறநானூறு","நற்றிணை"],"answer_index":2,"explanation":"புறநானூறு புறத்திணை (வீரம், கொடை, போர்) சார்ந்த பாடல்களைக் கொண்ட சங்க இலக்கியமாகும்.","difficulty":"easy"},{"question":"திருக்குறளில் 'இல்லறம்' குறித்து கூறும் அதிகாரம் எது?","options":["கள்ளுண்ணாமை","இல்வாழ்க்கை","அறன் வலியுறுத்தல்","துறவு"],"answer_index":1,"explanation":"திருக்குறளில் 'இல்வாழ்க்கை' எனும் அதிகாரம் இல்லற வாழ்க்கையின் சிறப்புகளை விளக்குகிறது. இது அறத்துப்பாலில் வரும் முதல் அதிகாரம்.","difficulty":"easy"},{"question":"எழுத்து, சொல், பொருள் என்ற மூன்று பிரிவுகளை உள்ளடக்கிய தமிழ் இலக்கண நூல் எது?","options":["தொல்காப்பியம்","நன்னூல்","வீரசோழியம்","யாப்பருங்கலம்"],"answer_index":0,"explanation":"தொல்காப்பியம் எழுத்ததிகாரம், சொல்லதிகாரம், பொருளதிகாரம் என மூன்று பிரிவுகளைக் கொண்ட முதல் தமிழ் இலக்கண நூலாகும்.","difficulty":"easy"},{"question":"திருவாசகம் இயற்றியவர் யார்?","options":["காரைக்கால் அம்மையார்","மாணிக்கவாசகர்","அப்பர்","சம்பந்தர்"],"answer_index":1,"explanation":"மாணிக்கவாசகர் இயற்றிய சிவபெருமான் மீதான பக்திப் பாடல்களின் தொகுப்பே திருவாசகம் ஆகும்.","difficulty":"easy"},{"question":"திருப்பாவை பாடிய ஆழ்வார் யார்?","options":["ஆண்டாள்","நம்மாழ்வார்","திருமழிசையாழ்வார்","பொய்கையாழ்வார்"],"answer_index":0,"explanation":"திருப்பாவை ஆண்டாள் இயற்றிய முப்பது பாடல்களைக் கொண்ட வைணவ பக்தி இலக்கியமாகும்.","difficulty":"easy"},{"question":"தேவாரம் இயற்றிய மூவரில் ஒருவர் அல்லாதவர் யார்?","options":["திருஞானசம்பந்தர்","திருநாவுக்கரசர்","சுந்தரர்","மாணிக்கவாசகர்"],"answer_index":3,"explanation":"தேவாரம் திருஞானசம்பந்தர், திருநாவுக்கரசர், சுந்தரர் ஆகிய மூவரால் இயற்றப்பட்டது. மாணிக்கவாசகர் திருவாசகம் இயற்றியவர்.","difficulty":"easy"},{"question":"பக்தி இலக்கியத்தில் 'திருவாசகம்' இயற்றியவர் யார்?","options":["மாணிக்கவாசகர்","திருஞானசம்பந்தர்","திருநாவுக்கரசர்","சுந்தரர்"],"answer_index":0,"explanation":"திருவாசகம் மாணிக்கவாசகரால் இயற்றப்பட்ட சைவ பக்தி இலக்கிய நூலாகும்.","difficulty":"medium"},{"question":"நாலாயிர திவ்யப் பிரபந்தத்தில் முதல் ஆயிரம் பாடல்களை இயற்றியவர் யார்?","options":["ஆண்டாள்","திருமங்கையாழ்வார்","பெரியாழ்வார்","நம்மாழ்வார்"],"answer_index":2,"explanation":"பெரியாழ்வார் (விஷ்ணுசித்தர்) நாலாயிர திவ்யப் பிரபந்தத்தின் முதல் ஆயிரம் பாடல்களை இயற்றியவர்.","difficulty":"medium"},{"question":"'தேவாரம்' என்னும் பக்தி இலக்கியத் தொகுப்பில் அடங்கியுள்ள மூவர் பாடல்கள் யாவை?","options":["திருஞானசம்பந்தர், திருநாவுக்கரசர், சுந்தரர்","மாணிக்கவாசகர், திருஞானசம்பந்தர், சுந்தரர்","திருநாவுக்கரசர், மாணிக்கவாசகர், காரைக்கால் அம்மையார்","சுந்தரர், திருஞானசம்பந்தர், ஆண்டாள்"],"answer_index":0,"explanation":"தேவாரம் என்பது திருஞானசம்பந்தர், திருநாவுக்கரசர், சுந்தரர் ஆகிய மூவரின் பாடல்களைக் கொண்ட தொகுப்பு.","difficulty":"medium"},{"question":"சைவ பக்தி இலக்கியத்தில் 'திருமுறை' என்பது எத்தனை நூல்களைக் கொண்டது?","options":["12","14","18","10"],"answer_index":0,"explanation":"சைவத் திருமுறை 12 நூல்களைக் கொண்டது; இதில் தேவாரம், திருவாசகம் முதலியன அடங்கும்.","difficulty":"medium"},{"question":"வைணவ பக்தி இலக்கியத்தில் 'இராமானுஜர்' எந்த நூலை இயற்றினார்?","options":["ஸ்ரீபாஷ்யம்","திருவாய்மொழி","பெரிய திருமொழி","திருப்பாவை"],"answer_index":0,"explanation":"இராமானுஜர் வைணவ சித்தாந்தத்தை விளக்கும் 'ஸ்ரீபாஷ்யம்' என்னும் நூலை இயற்றினார்.","difficulty":"medium"},{"question":"பக்தி இலக்கியத்தில் 'திருப்பாவை' இயற்றியவர் யார்?","options":["ஆண்டாள்","குலசேகராழ்வார்","தொண்டரடிப்பொடியாழ்வார்","மதுரகவி ஆழ்வார்"],"answer_index":0,"explanation":"திருப்பாவை ஆண்டாளால் இயற்றப்பட்ட 30 பாடல்களைக் கொண்ட வைணவ பக்தி நூலாகும்.","difficulty":"medium"},{"question":"சங்க இலக்கியத்தில் பக்தி கருத்துகளை முதன்முதலில் வெளிப்படுத்திய நூல் எது?","options":["பரிபாடல்","கலித்தொகை","அகநானூறு","புறநானூறு"],"answer_index":0,"explanation":"பரிபாடல் சங்க இலக்கியத்தில் திருமால், முருகன் மீதான பக்தியை வெளிப்படுத்தும் முதல் நூலாகும்.","difficulty":"medium"},{"question":"'திருக்குறள்' நூலில் 'அறத்துப்பால்' எத்தனை அதிகாரங்களைக் கொண்டது?","options":["38","25","40","35"],"answer_index":0,"explanation":"திருக்குறளில் அறத்துப்பால் 38 அதிகாரங்களையும், 380 குறள்களையும் கொண்டது.","difficulty":"medium"},{"question":"தமிழ் இலக்கணத்தில் 'எழுத்து' பற்றி விளக்கும் நூல் எது?","options":["தொல்காப்பியம் எழுத்ததிகாரம்","தொல்காப்பியம் சொல்லதிகாரம்","தொல்காப்பியம் பொருளதிகாரம்","நன்னூல்"],"answer_index":0,"explanation":"தொல்காப்பியத்தின் எழுத்ததிகாரம் தமிழ் எழுத்துகளின் இயல்புகளை விளக்குகிறது.","difficulty":"medium"},{"question":"பக்தி இலக்கியத்தில் 'காரைக்கால் அம்மையார்' இயற்றிய நூல் எது?","options":["திருவாலங்காட்டு மூத்த திருப்பதிகம்","திருவாசகம்","தேவாரம்","திருப்பாவை"],"answer_index":0,"explanation":"காரைக்கால் அம்மையார் சிவபெருமான் மீது 'திருவாலங்காட்டு மூத்த திருப்பதிகம்' என்னும் நூலை இயற்றினார்.","difficulty":"medium"},{"question":"பன்னிரு திருமுறைகளில் முதல் ஏழு திருமுறைகள் எந்த நூலின் பகுதியாகும்?","options":["திருவாசகம்","திவ்வியப் பிரபந்தம்","தேவாரம்","பெரிய புராணம்"],"answer_index":2,"explanation":"முதல் ஏழு திருமுறைகள் தேவாரம் எனப்படும். இது சம்பந்தர், நாவுக்கரசர், சுந்தரர் ஆகியோரின் பாடல்களைக் கொண்டுள்ளது.","difficulty":"medium"},{"question":"திருவாசகம் எந்த திருமுறையில் அடங்கும்?","options":["எட்டாம் திருமுறை","ஏழாம் திருமுறை","ஒன்பதாம் திருமுறை","பதினொன்றாம் திருமுறை"],"answer_index":0,"explanation":"திருவாசகம் எட்டாம் திருமுறையாகும். இது மாணிக்கவாசகரால் இயற்றப்பட்டது.","difficulty":"medium"},{"question":"ஆழ்வார்களின் பாடல்கள் அடங்கிய தொகுப்பு எவ்வாறு அழைக்கப்படுகிறது?","options":["நாலாயிர திவ்வியப் பிரபந்தம்","பன்னிரு திருமுறை","திருப்பாவை","பெரியாழ்வார் திருமொழி"],"answer_index":0,"explanation":"ஆழ்வார்களின் 4000 பாடல்கள் நாலாயிர திவ்வியப் பிரபந்தம் எனப்படும்.","difficulty":"medium"},{"question":"பெரிய புராணத்தை இயற்றியவர் யார்?","options":["சேக்கிழார்","கம்பர்","நம்பியாண்டார் நம்பி","மாணிக்கவாசகர்"],"answer_index":0,"explanation":"சேக்கிழார் பெரிய புராணத்தை இயற்றினார். இது 63 நாயன்மார்களின் வரலாற்றைக் கூறுகிறது.","difficulty":"medium"},{"question":"திருஞானசம்பந்தர், திருநாவுக்கரசர், சுந்தரர் ஆகிய மூவரும் எந்தப் பகுப்பில் அடங்குவர்?","options":["நாயன்மார்கள்","ஆழ்வார்கள்","சமண முனிவர்கள்","பௌத்தத் துறவிகள்"],"answer_index":0,"explanation":"இம்மூவரும் சைவ சமயத்தின் நாயன்மார்கள் ஆவர். இவர்கள் தேவாரம் இயற்றியவர்கள்.","difficulty":"medium"},{"question":"தேவாரத்தின் முதல் திருமுறையை இயற்றியவர் யார்?","options":["திருஞானசம்பந்தர்","திருநாவுக்கரசர்","சுந்தரர்","மாணிக்கவாசகர்"],"answer_index":0,"explanation":"முதல் திருமுறை திருஞானசம்பந்தர் இயற்றிய தேவாரப் பாடல்களைக் கொண்டுள்ளது.","difficulty":"medium"},{"question":"சைவத் திருமுறைகள் மொத்தம் எத்தனை?","options":["12","18","9","63"],"answer_index":0,"explanation":"சைவ சமயத்தில் பன்னிரு திருமுறைகள் உள்ளன. இவை தேவாரம், திருவாசகம் முதலியவற்றை உள்ளடக்கியது.","difficulty":"medium"},{"question":"நாலாயிர திவ்வியப் பிரபந்தத்தில் எத்தனை பாடல்கள் உள்ளன?","options":["4000","1000","400","3000"],"answer_index":0,"explanation":"நாலாயிர திவ்வியப் பிரபந்தம் 4000 பாடல்களைக் கொண்டுள்ளது. இது 12 ஆழ்வார்களின் பாடல்களின் தொகுப்பு.","difficulty":"medium"},{"question":"திருப்பாவை எழுதியவர் யார்?","options":["ஆண்டாள்","பெரியாழ்வார்","திருமழிசையாழ்வார்","நம்மாழ்வார்"],"answer_index":0,"explanation":"ஆண்டாள் திருப்பாவையை இயற்றினார். இது நாலாயிர திவ்வியப் பிரபந்தத்தின் ஒரு பகுதி.","difficulty":"medium"},{"question":"திருவெம்பாவை எந்த நூலின் பகுதி?","options":["தேவாரம்","திருவாசகம்","திருப்பாவை","பெரிய புராணம்"],"answer_index":1,"explanation":"திருவெம்பாவை திருவாசகத்தில் உள்ள பாடல்கள். இது மாணிக்கவாசகரால் இயற்றப்பட்டது.","difficulty":"medium"},{"question":"நாலாயிர திவ்ய பிரபந்தத்தில் முதல் ஆயிரம் பாடல்களை இயற்றியவர் யார்?","options":["ஆண்டாள்","திருமழிசையாழ்வார்","பெரியாழ்வார்","நம்மாழ்வார்"],"answer_index":2,"explanation":"பெரியாழ்வார் நாலாயிர திவ்ய பிரபந்தத்தில் முதல் ஆயிரம் பாடல்களை இயற்றியவர் ஆவார்.","difficulty":"medium"},{"question":"தேவாரம் என்பது எத்தனை திருமுறைகளை உள்ளடக்கியது?","options":["மூன்று","ஏழு","பன்னிரண்டு","ஐந்து"],"answer_index":0,"explanation":"தேவாரம் முதல் மூன்று திருமுறைகளை உள்ளடக்கிய சைவ பக்தி இலக்கியமாகும்.","difficulty":"medium"},{"question":"திருக்குறளில் 'அறத்துப்பால்' எத்தனை அதிகாரங்களைக் கொண்டுள்ளது?","options":["38","25","70","40"],"answer_index":0,"explanation":"திருக்குறளில் அறத்துப்பால் 38 அதிகாரங்களையும், 380 குறள்களையும் கொண்டுள்ளது.","difficulty":"medium"},{"question":"சங்க இலக்கியத்தில் 'புறநானூறு' எத்தனை பாடல்களைக் கொண்டுள்ளது?","options":["400","268","500","300"],"answer_index":1,"explanation":"புறநானூறு 268 பாடல்களைக் கொண்ட புறப்பொருள் பற்றிய சங்க இலக்கிய நூலாகும்.","difficulty":"medium"},{"question":"எழுத்து இலக்கணத்தில் 'உயிர்மெய்' எழுத்துகள் எத்தனை?","options":["216","12","18","247"],"answer_index":0,"explanation":"உயிர்மெய் எழுத்துகள் 12 உயிர்களும் 18 மெய்களும் சேர்ந்து 216 ஆகும்.","difficulty":"medium"},{"question":"திருக்குறளில் 'இனியவை கூறல்' எந்த அதிகாரத்தில் வருகிறது?","options":["இனியவை கூறல்","சொல்வன்மை","அறிவுடைமை","கல்லாமை"],"answer_index":0,"explanation":"திருக்குறளில் 10வது அதிகாரமான 'இனியவை கூறல்' இனிமையாகப் பேசுவதன் சிறப்பை விளக்குகிறது.","difficulty":"medium"},{"question":"சொல் இலக்கணத்தில் 'வேற்றுமை' எத்தனை வகைப்படும்?","options":["8","6","7","5"],"answer_index":0,"explanation":"தமிழ் இலக்கணத்தில் வேற்றுமை எட்டு வகைப்படும், அவை பெயருக்கும் வினைக்கும் உறவைக் காட்டுகின்றன.","difficulty":"medium"},{"question":"சங்க இலக்கியத்தில் 'ஐங்குறுநூறு' எந்த திணையைச் சார்ந்தது?","options":["அகம்","புறம்","கலம்பகம்","உரைநடை"],"answer_index":0,"explanation":"ஐங்குறுநூறு அகப்பொருள் பற்றிய சங்க இலக்கிய நூலாகும், இது 500 பாடல்களைக் கொண்டது.","difficulty":"medium"},{"question":"நாலாயிர திவ்ய பிரபந்தத்தில் உள்ள பாசுரங்களின் மொத்த எண்ணிக்கை என்ன?","options":["4000","3000","6000","1000"],"answer_index":0,"explanation":"நாலாயிர திவ்ய பிரபந்தம் 4000 பாசுரங்களைக் கொண்ட வைணவ பக்தி இலக்கியத் தொகுப்பாகும்.","difficulty":"medium"},{"question":"பக்தி இலக்கியத்தில் சைவ சமயத்தைச் சேர்ந்த நாயன்மார்களின் பாடல்கள் எந்த நூலில் தொகுக்கப்பட்டுள்ளன?","options":["தேவாரம்","திருவாசகம்","திவ்ய பிரபந்தம்","கம்பராமாயணம்"],"answer_index":0,"explanation":"சைவ நாயன்மார்கள் அறுபத்து மூவர் பாடிய பதிகங்கள் தேவாரம் எனத் தொகுக்கப்பட்டுள்ளன. திருவாசகம் மாணிக்கவாசகர் பாடியது.","difficulty":"medium"},{"question":"வைணவ பக்தி இலக்கியமான நாலாயிர திவ்ய பிரபந்தத்தை தொகுத்தவர் யார்?","options":["நாதமுனி","இராமானுஜர்","மணவாள மாமுனிகள்","வேதாந்த தேசிகர்"],"answer_index":0,"explanation":"நாலாயிர திவ்ய பிரபந்தத்தை ஆழ்வார்கள் பாடல்களைத் தொகுத்தவர் நாதமுனி ஆவார். இராமானுஜர் விசிஷ்டாத்வைதத்தை விளக்கியவர்.","difficulty":"medium"},{"question":"பன்னிரு திருமுறைகளில் முதல் மூன்று திருமுறைகள் எவ்வாறு அழைக்கப்படுகின்றன?","options":["திருவாசகம்","தேவாரம்","திருப்பாவை","நாலாயிர திவ்ய பிரபந்தம்"],"answer_index":1,"explanation":"முதல் மூன்று திருமுறைகளான சம்பந்தர், அப்பர், சுந்தரர் பாடல்கள் தேவாரம் எனப்படும்.","difficulty":"hard"},{"question":"கீழ்க்கண்டவர்களில் ஓர் ஆழ்வார் அல்லாதவர் யார்?","options":["நம்மாழ்வார்","பெரியாழ்வார்","ஆண்டாள்","மாணிக்கவாசகர்"],"answer_index":3,"explanation":"மாணிக்கவாசகர் சைவ நாயன்மார்களுள் ஒருவர்; ஆழ்வார்கள் வைணவப் பக்தி இலக்கியத்தைச் சேர்ந்தவர்.","difficulty":"hard"},{"question":"ஆழ்வார்களின் எண்ணிக்கை எவ்வளவு?","options":["12","63","18","9"],"answer_index":0,"explanation":"வைணவப் பக்தி இலக்கியத்தில் 12 ஆழ்வார்கள் உள்ளனர்.","difficulty":"hard"},{"question":"“குழலினிது யாழினிது என்பார்” என்ற தொடர் எந்த நூலில் இடம்பெற்றுள்ளது?","options":["தேவாரம்","திருவாசகம்","திருப்பாவை","திருவெம்பாவை"],"answer_index":1,"explanation":"இது மாணிக்கவாசகரின் திருவாசகத்தில் வரும் புகழ்பெற்ற வரி.","difficulty":"hard"},{"question":"திருநாவுக்கரசர் என்று அழைக்கப்படும் சைவ நாயன்மார் யார்?","options":["சம்பந்தர்","அப்பர்","சுந்தரர்","மாணிக்கவாசகர்"],"answer_index":1,"explanation":"அப்பர் திருநாவுக்கரசர் எனும் பெயரால் அறியப்படுகிறார்.","difficulty":"hard"},{"question":"ஆழ்வார்களின் 4000 பாடல்கள் அடங்கிய தொகுப்பின் பெயர் என்ன?","options":["திருமுறை","நாலாயிர திவ்ய பிரபந்தம்","தேவாரம்","பன்னிரு திருமுறை"],"answer_index":1,"explanation":"நாலாயிர திவ்ய பிரபந்தம் வைணவ ஆழ்வார்களின் பாடல்களைக் கொண்ட தொகுப்பு.","difficulty":"hard"},{"question":"ஆண்டாள் இயற்றிய நூல் எது?","options":["திருப்பாவை","திருவெம்பாவை","திருக்குறள்","சிலப்பதிகாரம்"],"answer_index":0,"explanation":"ஆண்டாள் இயற்றிய திருப்பாவை வைணவப் பக்தி இலக்கியத்தின் முக்கிய நூல்.","difficulty":"hard"},{"question":"திருமந்திரம் இயற்றியவர் யார்?","options":["திருமூலர்","பட்டினத்தார்","காரைக்கால் அம்மையார்","சிவவாக்கியர்"],"answer_index":0,"explanation":"திருமந்திரம் திருமூலர் இயற்றிய சைவத் திருமுறை நூலாகும்.","difficulty":"hard"},{"question":"நாலாயிர திவ்ய பிரபந்தத்தில் முதல் மூன்று ஆழ்வார்கள் யாவர்?","options":["பொய்கை, பூதம், பேய்","நம்மாழ்வார், பெரியாழ்வார், ஆண்டாள்","திருமங்கை, தொண்டரடிப்பொடி, திருப்பாண்","குலசேகரன், விஷ்ணுசித்தன், மதுரகவி"],"answer_index":0,"explanation":"முதல் மூன்று ஆழ்வார்கள் பொய்கையாழ்வார், பூதத்தாழ்வார், பேயாழ்வார் ஆவர்.","difficulty":"hard"},{"question":"தேவாரத் திருமுறைகளைத் தொகுத்து அருளிச்செய்தவர் யார்?","options":["நம்பியாண்டார் நம்பி","சேக்கிழார்","திருநாவுக்கரசர்","சுந்தரர்"],"answer_index":0,"explanation":"நம்பியாண்டார் நம்பி தேவாரத் திருமுறைகளைத் தொகுத்து அருளிச்செய்தவர் ஆவார்.","difficulty":"hard"},{"question":"பன்னிரு ஆழ்வார்களில் இறுதியாகத் தோன்றியவர் யார்?","options":["திருமங்கையாழ்வார்","ஆண்டாள்","தொண்டரடிப்பொடியாழ்வார்","நம்மாழ்வார்"],"answer_index":0,"explanation":"திருமங்கையாழ்வார் பன்னிரு ஆழ்வார்களில் இறுதியாகத் தோன்றியவர் ஆவார்.","difficulty":"hard"},{"question":"திருவாசகத்தின் முதல் பாடல் எது?","options":["சிவபுராணம்","கோயில் மூத்த திருப்பதிகம்","திருவெம்பாவை","திருச்சதகம்"],"answer_index":0,"explanation":"திருவாசகத்தின் முதல் பாடல் 'சிவபுராணம்' ஆகும்.","difficulty":"hard"},{"question":"திருக்குறளில் 'அறத்துப்பால்' எத்தனை அதிகாரங்களைக் கொண்டது?","options":["38","40","35","42"],"answer_index":0,"explanation":"திருக்குறளில் அறத்துப்பால் 38 அதிகாரங்களைக் கொண்டது.","difficulty":"hard"},{"question":"பக்தி இலக்கியத்தில் 'திருவாய்மொழி' இயற்றியவர் யார்?","options":["நம்மாழ்வார்","திருமழிசையாழ்வார்","பூதத்தாழ்வார்","பேயாழ்வார்"],"answer_index":0,"explanation":"நம்மாழ்வார் 'திருவாய்மொழி' என்னும் நூலை இயற்றியவர் ஆவார்.","difficulty":"hard"},{"question":"சேக்கிழார் இயற்றிய பெரியபுராணத்தில் எத்தனை நாயன்மார்களின் வரலாறு கூறப்படுகிறது?","options":["63","12","9","27"],"answer_index":0,"explanation":"பெரியபுராணத்தில் 63 நாயன்மார்களின் வரலாறு கூறப்படுகிறது.","difficulty":"hard"},{"question":"தேவாரத்தில் 'திருஞானசம்பந்தர்' பாடிய பதிகங்களின் எண்ணிக்கை எவ்வளவு?","options":["384","200","150","400"],"answer_index":0,"explanation":"திருஞானசம்பந்தர் 384 பதிகங்களைப் பாடியுள்ளார்.","difficulty":"hard"},{"question":"திருக்குறளில் 'இயற்கைப் புணர்ச்சி' என்னும் அதிகாரம் எந்தப் பாலில் உள்ளது?","options":["காமத்துப்பால்","அறத்துப்பால்","பொருட்பால்","இல்லை"],"answer_index":0,"explanation":"இயற்கைப் புணர்ச்சி அதிகாரம் காமத்துப்பாலில் உள்ளது.","difficulty":"hard"},{"question":"திருவாசகத்தில் 'திருச்சதகம்' எத்தனை பாடல்களைக் கொண்டது?","options":["100","50","200","150"],"answer_index":0,"explanation":"திருச்சதகம் 100 பாடல்களைக் கொண்டது.","difficulty":"hard"},{"question":"தமிழில் பக்தி இலக்கியத்தில், தேவாரம் இயற்றப்பட்ட மூவர் (சமயாச்சாரியர்கள்) யாவர்?","options":["அப்பர், சம்பந்தர், சுந்தரர்","மாணிக்கவாசகர், சம்பந்தர், சுந்தரர்","அப்பர், சம்பந்தர், மாணிக்கவாசகர்","சுந்தரர், மாணிக்கவாசகர், அப்பர்"],"answer_index":0,"explanation":"தேவாரம் அப்பர், சம்பந்தர், சுந்தரர் ஆகிய மூவரால் இயற்றப்பட்டது; மாணிக்கவாசகர் திருவாசகம் இயற்றினார்.","difficulty":"hard"},{"question":"நாலாயிர திவ்யப் பிரபந்தத்தில் உள்ள பாசுரங்களின் மொத்த எண்ணிக்கை எவ்வளவு?","options":["4000","400","40000","400000"],"answer_index":0,"explanation":"நாலாயிர திவ்யப் பிரபந்தம் நான்காயிரம் பாசுரங்களைக் கொண்டது; இது 12 ஆழ்வார்களால் இயற்றப்பட்டது.","difficulty":"hard"},{"question":"கீழ்க்கண்டவர்களில் சைவ சமயத்தைச் சேர்ந்தவர் அல்லாதவர் யார்?","options":["திருஞானசம்பந்தர்","திருநாவுக்கரசர்","நம்மாழ்வார்","சுந்தரர்"],"answer_index":2,"explanation":"நம்மாழ்வார் வைணவ ஆழ்வார்; மற்றவர்கள் சைவ நாயன்மார்கள்.","difficulty":"hard"}]}